whale_interactive_feedback/__init__.py
whale_interactive_feedback/cli.py
whale_interactive_feedback/config.py
whale_interactive_feedback/downloader.py
whale_mcp_feedback-1.0.0.dist-info/METADATA
whale_mcp_feedback-1.0.0.dist-info/WHEEL
whale_mcp_feedback-1.0.0.dist-info/entry_points.txt
whale_mcp_feedback-1.0.0.dist-info/top_level.txt
whale_mcp_feedback-1.0.0.dist-info/RECORD
