Metadata-Version: 2.4
Name: whale-mcp-feedback
Version: 1.0.0
Summary: MCP server for interactive user feedback with GUI - Python wrapper for Rust binary
Author: whalesea1314
License-Expression: MIT
Project-URL: Homepage, https://github.com/whalesea1314/whale-interactive-feedback
Project-URL: Repository, https://github.com/whalesea1314/whale-interactive-feedback
Project-URL: Issues, https://github.com/whalesea1314/whale-interactive-feedback/issues
Keywords: mcp,ai,feedback,interactive,cursor,claude,kiro
Classifier: Development Status :: 4 - Beta
Classifier: Intended Audience :: Developers
Classifier: Operating System :: OS Independent
Classifier: Programming Language :: Python :: 3
Classifier: Programming Language :: Python :: 3.10
Classifier: Programming Language :: Python :: 3.11
Classifier: Programming Language :: Python :: 3.12
Classifier: Topic :: Software Development
Classifier: Topic :: Scientific/Engineering :: Artificial Intelligence
Requires-Python: >=3.10
Requires-Dist: httpx>=0.25.0
Requires-Dist: platformdirs>=4.0.0
Provides-Extra: socks
Requires-Dist: httpx[socks]>=0.25.0; extra == "socks"
